dsdl/lab7/bcdToE3.v
module bcdToE3(b,x);
    input [3:0] b;
    output [3:0] x;
    wire [2:0] s;
    assign s = {b[2],b[1],b[0]};

    mux8to1 stage0({~b[3],~b[3],~b[3],1'b0,1'b0,1'b0,b[3],b[3]},s,x[3]);
    mux8to1 stage1({1'b0,1'b0,1'b0,~b[3],~b[3],~b[3],1'b1,1'b0},s,x[2]);
    mux8to1 stage2({~b[3],1'b0,1'b0,~b[3],~b[3],1'b0,1'b0,1'b1},s,x[1]);
    mux8to1 stage3({1'b0,~b[3],1'b0,~b[3],1'b0,~b[3],1'b0,1'b1},s,x[0]);

endmodule

module mux8to1(w,s,f);
    input [7:0] w;
    input [2:0] s;
    output f;
    reg f;

    always @(w or s)
    case (s)
        0: f = w[0];
        1: f = w[1];
        2: f = w[2];
        3: f = w[3];
        4: f = w[4];
        5: f = w[5];
        6: f = w[6];
        7: f = w[7];         
    endcase

endmodule

dsdl/lab7/bcdToE3_tb.v
`timescale 1ns/1ns
`include "bcdToE3.v"

module bcdToE3_tb();
reg [3:0] w;
wire [3:0] x;

bcdToE3 q(w,x);
initial
begin 

    $dumpfile("bcdToE3_tb.vcd");
    $dumpvars(0,bcdToE3_tb);

    w = 4'b0000; #20;
    w = 4'b0001; #20;
    w = 4'b0010; #20;
    w = 4'b0011; #20;
    w = 4'b0100; #20;
    w = 4'b0101; #20;
    w = 4'b0110; #20;
    w = 4'b0111; #20;
    w = 4'b1000; #20;
    w = 4'b1001; #20;

    $display("test complete");

end
endmodule

dsdl/lab7/bcdToE3_tb.vcd
$date
	Thu Oct 20 09:09:18 2022
$end
$version
	Icarus Verilog
$end
$timescale
	1ns
$end
$scope module bcdToE3_tb $end
$var wire 4 ! x [3:0] $end
$var reg 4 " w [3:0] $end
$scope module q $end
$var wire 4 # b [3:0] $end
$var wire 4 $ x [3:0] $end
$var wire 3 % s [2:0] $end
$scope module stage0 $end
$var wire 3 & s [2:0] $end
$var wire 8 ' w [7:0] $end
$var reg 1 ( f $end
$upscope $end
$scope module stage1 $end
$var wire 3 ) s [2:0] $end
$var wire 8 * w [7:0] $end
$var reg 1 + f $end
$upscope $end
$scope module stage2 $end
$var wire 3 , s [2:0] $end
$var wire 8 - w [7:0] $end
$var reg 1 . f $end
$upscope $end
$scope module stage3 $end
$var wire 3 / s [2:0] $end
$var wire 8 0 w [7:0] $end
$var reg 1 1 f $end
$upscope $end
$upscope $end
$upscope $end
$enddefinitions $end
#0
$dumpvars
11
b1010101 0
b0 /
1.
b10011001 -
b0 ,
0+
b11110 *
b0 )
0(
b11100000 '
b0 &
b0 %
b11 $
b0 #
b0 "
b11 !
$end
#20
1+
0.
b100 !
b100 $
01
b1 %
b1 &
b1 )
b1 ,
b1 /
b1 "
b1 #
#40
b101 !
b101 $
11
b10 %
b10 &
b10 )
b10 ,
b10 /
b10 "
b10 #
#60
1.
b110 !
b110 $
01
b11 %
b11 &
b11 )
b11 ,
b11 /
b11 "
b11 #
#80
b111 !
b111 $
11
b100 %
b100 &
b100 )
b100 ,
b100 /
b100 "
b100 #
#100
1(
0+
0.
b1000 !
b1000 $
01
b101 %
b101 &
b101 )
b101 ,
b101 /
b101 "
b101 #
#120
b1001 !
b1001 $
11
b110 %
b110 &
b110 )
b110 ,
b110 /
b110 "
b110 #
#140
1.
b1010 !
b1010 $
01
b111 %
b111 &
b111 )
b111 ,
b111 /
b111 "
b111 #
#160
b1011 !
b1011 $
11
b10 *
b1 -
b1 0
b0 %
b0 &
b0 )
b0 ,
b0 /
b11 '
b1000 "
b1000 #
#180
1+
0.
b1100 !
b1100 $
01
b1 %
b1 &
b1 )
b1 ,
b1 /
b1001 "
b1001 #
