dsdl/lab7/q2a.v
module q2a(w,f);
    input [2:0] w;
    output f;

    mux2to1 stage0(w[1:0],w[2],f);

endmodule

module mux2to1(w,s,f);
    input [1:0] w;
    input s;
    output reg f;

    always @(w or s)
    begin 
        f = w[0] | w[1];
        if(s == 0)
            f = w[0] & w[1];
    end
endmodule

dsdl/lab7/q2a_tb.v
`timescale 1ns/1ns
`include "q2a.v"

module q2a_tb();
reg [2:0] w;
wire f;

q2a q(w,f);
initial
begin 

    $dumpfile("q2a_tb.vcd");
    $dumpvars(0,q2a_tb);

    w = 3'b000; #20;
    w = 3'b001; #20;
    w = 3'b010; #20;
    w = 3'b011; #20;
    w = 3'b100; #20;
    w = 3'b101; #20;
    w = 3'b110; #20;
    w = 3'b111; #20;

    $display("test complete");

end
endmodule

dsdl/lab7/q2a_tb.vcd
$date
	Thu Oct 20 09:06:10 2022
$end
$version
	Icarus Verilog
$end
$timescale
	1ns
$end
$scope module q2a_tb $end
$var wire 1 ! f $end
$var reg 3 " w [2:0] $end
$scope module q $end
$var wire 3 # w [2:0] $end
$var wire 1 ! f $end
$scope module stage0 $end
$var wire 1 $ s $end
$var wire 2 % w [1:0] $end
$var reg 1 ! f $end
$upscope $end
$upscope $end
$upscope $end
$enddefinitions $end
#0
$dumpvars
b0 %
0$
b0 #
b0 "
0!
$end
#20
0!
b1 %
b1 "
b1 #
#40
0!
b10 %
b10 "
b10 #
#60
1!
b11 %
b11 "
b11 #
#80
0!
b0 %
1$
b100 "
b100 #
#100
1!
b1 %
b101 "
b101 #
#120
b10 %
b110 "
b110 #
#140
b11 %
b111 "
b111 #
