dsdl/lab1/q1.v
module q1(a, b, c,d, m);

input a, b,c,d;
output m;

and (g, a, b);
and (f, a,b);
or (h,g,c);
not (j,h);
and (k,j,d);
or (i,c,f);
or (l,d,i);
and(m,l,k);

endmodule

dsdl/lab1/q1_tb.v
`timescale 1ns/1ns
`include "q1.v"
//Name of the Verilog file
module q1_tb();
reg a,b,c,d;
//Input
wire m;
//Output
q1 ex1(a,b,c,d,m); //Instantiation of the module
initial
begin
$dumpfile("q1_tb.vcd");
$dumpvars(0, q1_tb);
a=1'b0; b=1'b0; c=1'b0;d=1'b0;
#20;
a=1'b0; b=1'b0; c=1'b0;d=1'b1;
#20;
a=1'b0; b=1'b0; c=1'b1;d=1'b0;
#20;
a=1'b0; b=1'b0; c=1'b1;d=1'b1;
#20;
a=1'b0; b=1'b1; c=1'b0;d=1'b0;
#20;
a=1'b0; b=1'b1; c=1'b0;d=1'b1;
#20;
a=1'b0; b=1'b1; c=1'b1;d=1'b0;
#20;
a=1'b0; b=1'b1; c=1'b1;d=1'b1;
#20;
a=1'b1; b=1'b0; c=1'b0;d=1'b0;
#20;
a=1'b1; b=1'b0; c=1'b0;d=1'b1;
#20;
a=1'b1; b=1'b0; c=1'b1;d=1'b0;
#20;
a=1'b1; b=1'b0; c=1'b1;d=1'b1;
#20;
a=1'b1; b=1'b1; c=1'b0;d=1'b0;
#20;
a=1'b1; b=1'b1; c=1'b0;d=1'b1;
#20;

a=1'b1; b=1'b1; c=1'b1;d=1'b0;
#20;
a=1'b1; b=1'b1; c=1'b1;d=1'b1;
#20;

$display("Test complete");
end
endmodule

dsdl/lab1/q1_tb.vcd
$date
	Thu Aug 25 09:37:05 2022
$end
$version
	Icarus Verilog
$end
$timescale
	1ns
$end
$scope module q1_tb $end
$var wire 1 ! m $end
$var reg 1 " a $end
$var reg 1 # b $end
$var reg 1 $ c $end
$var reg 1 % d $end
$scope module ex1 $end
$var wire 1 " a $end
$var wire 1 # b $end
$var wire 1 $ c $end
$var wire 1 % d $end
$var wire 1 & f $end
$var wire 1 ' g $end
$var wire 1 ( h $end
$var wire 1 ) i $end
$var wire 1 * j $end
$var wire 1 + k $end
$var wire 1 , l $end
$var wire 1 ! m $end
$upscope $end
$upscope $end
$enddefinitions $end
#0
$dumpvars
0,
0+
1*
0)
0(
0'
0&
0%
0$
0#
0"
0!
$end
#20
1!
1+
1,
1%
#40
0!
0*
0+
1(
1)
0%
1$
#60
1%
#80
1*
0,
0(
0)
0%
0$
1#
#100
1!
1+
1,
1%
#120
0!
0*
0+
1(
1)
0%
1$
#140
1%
#160
1*
0,
0(
0)
0%
0$
0#
1"
#180
1!
1+
1,
1%
#200
0!
0*
0+
1(
1)
0%
1$
#220
1%
#240
1'
1&
0%
0$
1#
#260
1%
#280
0%
1$
#300
1%
