dsdl/lab2/q1.v
module q1(a,b,c,d,f1,f11,f2,f22);
input a,b,c,d;
output f1,f11,f2,f22;
assign f1=(~a&b)|(b&~c&~d)|(c&d)|(~b&c);
assign f2=(b&~c&~d)|(~b&d)|(~b&c);
and(k1,~a,b);
and(k2,c,d);
and(k3,~b,c);
and(k4,b,~c,~d);
or(f11,k1,k2,k3,k4);
and(n1,b,~c,~d);
and(n2,~b,d);
and(n3,~b,c);
or(f22,n1,n2,n3);
endmodule

dsdl/lab2/q1_tb.v
`timescale 1ns/1ns
`include "q1.v"
 
module q1_tb;
 
reg a,b,c,d;
wire f1,f11,f2,f22;

q1 uut(a,b,c,d,f1,f11,f2,f22);
initial begin
 
$dumpfile("q1_tb.vcd");
$dumpvars(0,q1_tb);
 
a=0;
b=0;
c=0;
d=0;
#20;
 
a=0;
b=0; 
c=0;
d=1;
#20;
 
a=0;
b=0;
c=1;
d=0;
#20;
 
a=0;
b=0;
c=1;
d=1;
#20;
 
a=0;
b=1;
c=0;
d=0;
#20;
 
a=0;
b=1;
c=0;
d=1;
#20;
 
a=0;
b=1;
c=1;
d=0;
#20;
 
a=0;
b=1;
c=1;
d=1;
#20;
 
a=1;
b=0;
c=0;
d=0;
#20;
 
a=1;
b=0;
c=0;
d=1;
#20;
 
a=1;
b=0;
c=1;
d=0;
#20;
 
a=1;
b=0;
c=1;
d=1;
#20;
 
a=1;
b=1;
c=0;
d=0;
#20;
 
a=1;
b=1;
c=0;
d=1;
#20;
 
a=1;
b=1;
c=1;
d=0;
#20;
 
a=1;
b=1;
c=1;
d=1;
#20;
 
$display("test complete");
end
 
endmodule

dsdl/lab2/q1_tb.vcd
$date
	Thu Sep  1 09:02:32 2022
$end
$version
	Icarus Verilog
$end
$timescale
	1ns
$end
$scope module q1_tb $end
$var wire 1 ! f22 $end
$var wire 1 " f2 $end
$var wire 1 # f11 $end
$var wire 1 $ f1 $end
$var reg 1 % a $end
$var reg 1 & b $end
$var reg 1 ' c $end
$var reg 1 ( d $end
$scope module uut $end
$var wire 1 % a $end
$var wire 1 & b $end
$var wire 1 ' c $end
$var wire 1 ( d $end
$var wire 1 $ f1 $end
$var wire 1 # f11 $end
$var wire 1 " f2 $end
$var wire 1 ! f22 $end
$var wire 1 ) k1 $end
$var wire 1 * k2 $end
$var wire 1 + k3 $end
$var wire 1 , k4 $end
$var wire 1 - n1 $end
$var wire 1 . n2 $end
$var wire 1 / n3 $end
$upscope $end
$upscope $end
$enddefinitions $end
#0
$dumpvars
0/
0.
0-
0,
0+
0*
0)
0(
0'
0&
0%
0$
0#
0"
0!
$end
#20
1"
1!
1.
1(
#40
1$
1#
0.
1+
1/
0(
1'
#60
1*
1.
1(
#80
1"
1,
1-
1!
0.
0*
0+
0/
1)
0(
0'
1&
#100
0"
0!
0,
0-
1(
#120
0(
1'
#140
1*
1(
#160
0$
0#
0*
0)
0(
0'
0&
1%
#180
1"
1!
1.
1(
#200
1$
1#
0.
1+
1/
0(
1'
#220
1*
1.
1(
#240
1"
1$
1,
1-
1!
0.
0*
0+
0/
0(
0'
1&
#260
0$
0"
0#
0!
0,
0-
1(
#280
0(
1'
#300
1$
1#
1*
1(
