dsdl/lab7/q1a.v
module q1a(a,b,c,d,f);
    input a,b,c,d;
    output f;
    wire [2:0] h;
    assign h = {a,b,c};

    mux8to1 stage01(~d,h,f);
    
endmodule

module mux8to1(notd,s,f);
    input notd;
    input [2:0] s;
    output reg f;

    always @(s)
    case (s)
        0: f = 0;
        1: f = 0;
        2: f = 1;
        3: f = 1;
        4: f = 1;
        5: f = 0;
        6: f = 1;
        7: f = notd;         
    endcase

endmodule

dsdl/lab7/q1a_tb.v
`timescale 1ns/1ns
`include "q1a.v"

module q1a_tb();
reg a,b,c,d;
wire f;

q1a q(a,b,c,d,f);
initial 
begin 
    $dumpfile("q1a_tb.vcd");
    $dumpvars(0,q1a_tb);

	a=0; b=0; c=0; d=0;#20;
	a=0; b=0; c=0; d=1;#20;
	a=0; b=0; c=1; d=0;#20;
	a=0; b=0; c=1; d=1;#20;
	a=0; b=1; c=0; d=0;#20;
	a=0; b=1; c=0; d=1;#20;
	a=0; b=1; c=1; d=0;#20;
	a=0; b=1; c=1; d=1;#20;
	a=1; b=0; c=0; d=0;#20;
	a=1; b=0; c=0; d=1;#20;
	a=1; b=0; c=1; d=0;#20;
	a=1; b=0; c=1; d=1;#20;
	a=1; b=1; c=0; d=0;#20;
	a=1; b=1; c=0; d=1;#20;
	a=1; b=1; c=1; d=0;#20;
	a=1; b=1; c=1; d=1;#20;
    
	$display("test complete");

end
endmodule

dsdl/lab2/q1a_tb.vcd
$date
	Thu Sep  1 10:02:15 2022
$end
$version
	Icarus Verilog
$end
$timescale
	1ns
$end
$scope module q1a_tb $end
$var wire 1 ! f $end
$var reg 1 " a $end
$var reg 1 # b $end
$var reg 1 $ c $end
$var reg 1 % d $end
$scope module q1 $end
$var wire 1 " a $end
$var wire 1 # b $end
$var wire 1 $ c $end
$var wire 1 % d $end
$var wire 1 ! f $end
$upscope $end
$upscope $end
$enddefinitions $end
#0
$dumpvars
0%
0$
0#
0"
0!
$end
#20
1%
#40
1!
0%
1$
#60
1%
#80
0%
0$
1#
#100
1%
#120
0%
1$
#140
1%
#160
0!
0%
0$
0#
1"
#180
1%
#200
1!
0%
1$
#220
1%
#240
0%
0$
1#
#260
0!
1%
#280
0%
1$
#300
1!
1%
