dsdl/lab2/q2.v
module q2( a,b,c,d,k1,k2,k3,k4);
input a,b,c,d;
output k1,k2,k3,k4;
assign k1=(b|c)&(~b|d);
assign k3=(a|~c|d)&(b|~c|d)&(a|~b|~d)&(~b|c|d);
or(f1,b,c);
or(f2,~b,d);
and(k2,f1,f2);
or(f3,a,~c,d);
or(f4,b,~c,d);
or(f5,a,~b,~d);
or(f6,~b,c,d);
and(k4,f3,f4,f5,f6);
endmodule

dsdl/lab2/q2_tb.v
`timescale 1ns/1ns
`include"q2.v"
module q2_tb;
reg a,b,c,d;
wire k1,k2,k3,k4;
q2 uut(a,b,c,d,k1,k2,k3,k4);
initial begin
$dumpfile("q2_tb.vcd");
$dumpvars(0,q2_tb);

a=0;
b=0;
c=0;
d=0;
#20;

a=0;	
b=0;
c=0;
d=1;
#20;

a=0;
b=0;
c=1;
d=0;
#20;

a=0;
b=1;
c=0;
d=0;
#20;

a=0;
b=0;
c=1;
d=1;
#20;

a=0;
b=1;
c=0;
d=1;
#20;

a=0;
b=1;
c=1;
d=0;
#20;

a=0;
b=1;
c=1;
d=1;
#20;

a=1;
b=0;
c=0;
d=0;
#20;

a=1;
b=0;
c=0;
d=1;
#20;

a=1;
b=0;
c=1;
d=0;
#20;

a=1;
b=0;
c=1;
d=1;
#20;


a=1;
b=1;
c=0;
d=0;
#20;

a=1;
b=1;
c=0;
d=1;
#20;

a=1;
b=1;
c=1;
d=0;
#20;

a=1;
b=1;
c=1;
d=1;
#20;

$display("test complete");
end
endmodule

dsdl/lab2/q2_tb.vcd
$date
	Thu Sep  1 09:10:58 2022
$end
$version
	Icarus Verilog
$end
$timescale
	1ns
$end
$scope module q2_tb $end
$var wire 1 ! k4 $end
$var wire 1 " k3 $end
$var wire 1 # k2 $end
$var wire 1 $ k1 $end
$var reg 1 % a $end
$var reg 1 & b $end
$var reg 1 ' c $end
$var reg 1 ( d $end
$scope module uut $end
$var wire 1 % a $end
$var wire 1 & b $end
$var wire 1 ' c $end
$var wire 1 ( d $end
$var wire 1 ) f1 $end
$var wire 1 * f2 $end
$var wire 1 + f3 $end
$var wire 1 , f4 $end
$var wire 1 - f5 $end
$var wire 1 . f6 $end
$var wire 1 $ k1 $end
$var wire 1 # k2 $end
$var wire 1 " k3 $end
$var wire 1 ! k4 $end
$upscope $end
$upscope $end
$enddefinitions $end
#0
$dumpvars
1.
1-
1,
1+
1*
0)
0(
0'
0&
0%
0$
0#
1"
1!
$end
#20
1(
#40
0"
0!
1$
1#
0+
0,
1)
0(
1'
#60
0$
0#
1+
0*
0.
1,
0'
1&
#80
1$
1"
1#
1!
1*
1.
1(
1'
0&
#100
0"
0!
0-
0'
1&
#120
0"
0$
0#
1-
0*
0+
0(
1'
#140
1$
1#
0-
1*
1+
1(
#160
1"
1!
0$
0#
0)
1,
1-
0(
0'
0&
1%
#180
1(
#200
0"
0!
1$
1#
0,
1)
0(
1'
#220
1"
1!
1,
1(
#240
0$
0"
0#
0!
0*
0.
0(
0'
1&
#260
1$
1"
1#
1!
1*
1.
1(
#280
0$
0#
0*
0(
1'
#300
1$
1#
1*
1(
