dsdl/lab2/q3.v
module q3(a,b,c,d,f);
input a,b,c,d;
output f;
and(k1,b,c,d);
and(k2,a,c,d);
and(k3,a,b,d);
and(k4,a,b,c);
or(f,k1,k2,k3,k4);
endmodule

dsdl/lab2/q3_tb.v
`timescale 1ns/1ns
`include"q3.v"
module q3_tb;
reg a,b,c,d;
wire f;
q3 uut(a,b,c,d,f);
initial begin
$dumpfile("q3_tb.vcd");
$dumpvars(0,q3_tb);

a=0;
b=0;
c=0;
d=0;
#20;

a=0;	
b=0;
c=0;
d=1;
#20;

a=0;
b=0;
c=1;
d=0;
#20;



a=0;
b=1;
c=0;
d=0;
#20;

a=1;
b=0;
c=0;
d=0;
#20;

a=1;
b=0;
c=0;
d=1;
#20;

a=1;
b=0;
c=1;
d=1;
#20;

a=1;
b=1;
c=0;
d=0;
#20;

a=1;
b=1;
c=0;
d=1;
#20;

a=1;
b=1;
c=1;
d=0;
#20;

a=1;
b=0;
c=1;
d=1;
#20;

a=0;
b=1;
c=1;
d=1;
#20;


$display("test complete");
end
endmodule

dsdl/lab2/q3_tb.vcd
$date
	Thu Sep  1 09:14:07 2022
$end
$version
	Icarus Verilog
$end
$timescale
	1ns
$end
$scope module q3_tb $end
$var wire 1 ! f $end
$var reg 1 " a $end
$var reg 1 # b $end
$var reg 1 $ c $end
$var reg 1 % d $end
$scope module uut $end
$var wire 1 " a $end
$var wire 1 # b $end
$var wire 1 $ c $end
$var wire 1 % d $end
$var wire 1 ! f $end
$var wire 1 & k1 $end
$var wire 1 ' k2 $end
$var wire 1 ( k3 $end
$var wire 1 ) k4 $end
$upscope $end
$upscope $end
$enddefinitions $end
#0
$dumpvars
0)
0(
0'
0&
0%
0$
0#
0"
0!
$end
#20
1%
#40
0%
1$
#60
0$
1#
#80
0#
1"
#100
1%
#120
1!
1'
1$
#140
0!
0'
0%
0$
1#
#160
1!
1(
1%
#180
0(
1)
0%
1$
#200
1'
0)
1%
0#
#220
1&
0'
1#
0"
