dsdl/lab11/johnsonctr.v
module johnsonctr(clock,set,Resetn,Q);
input set,clock,Resetn;
output [4:0]Q;
dff s0(~Q[0],clock,set,Resetn,Q[4]);
dff s1(Q[4],clock,~set,Resetn,Q[3]);
dff s2(Q[3],clock,~set,Resetn,Q[2]);
dff s3(Q[2],clock,~set,Resetn,Q[1]);
dff s4(Q[1],clock,~set,Resetn,Q[0]);
endmodule

module dff(D,clock,set,Resetn,Q);
input D,set,clock,Resetn;
output reg Q;
always @ (posedge clock )
begin
if(!Resetn && set)
	Q <= 1;
else if(!Resetn)
	Q <= 0;
else
	Q <= D;
end
endmodule

dsdl/lab11/johnsonctr_tb.v
`timescale 1ns/1ns
`include "johnsonctr.v"
module johnsonctr_tb();
reg set,clock, Resetn;
wire[4:0] Q;
integer i;
johnsonctr q2(clock,set,Resetn,Q);

initial
begin
$dumpfile("johnsonctr_tb.vcd");
$dumpvars(0, johnsonctr_tb);
clock=0;
forever #20 clock = ~clock;
end

initial
begin
Resetn=0; set=1; #40;
repeat ( 2 )
begin
Resetn=1; set=0; #200;
end
#20;
$display("test complete");
$finish;
end
endmodule

dsdl/lab11/johnsonctr_tb.vcd
$date
	Thu Nov 17 11:10:47 2022
$end
$version
	Icarus Verilog
$end
$timescale
	1ns
$end
$scope module johnsonctr_tb $end
$var wire 5 ! Q [4:0] $end
$var reg 1 " Resetn $end
$var reg 1 # clock $end
$var reg 1 $ set $end
$scope module q2 $end
$var wire 1 " Resetn $end
$var wire 1 # clock $end
$var wire 1 $ set $end
$var wire 5 % Q [4:0] $end
$scope module s0 $end
$var wire 1 & D $end
$var wire 1 " Resetn $end
$var wire 1 # clock $end
$var wire 1 $ set $end
$var reg 1 ' Q $end
$upscope $end
$scope module s1 $end
$var wire 1 ( D $end
$var wire 1 " Resetn $end
$var wire 1 # clock $end
$var wire 1 ) set $end
$var reg 1 * Q $end
$upscope $end
$scope module s2 $end
$var wire 1 + D $end
$var wire 1 " Resetn $end
$var wire 1 # clock $end
$var wire 1 , set $end
$var reg 1 - Q $end
$upscope $end
$scope module s3 $end
$var wire 1 . D $end
$var wire 1 " Resetn $end
$var wire 1 # clock $end
$var wire 1 / set $end
$var reg 1 0 Q $end
$upscope $end
$scope module s4 $end
$var wire 1 1 D $end
$var wire 1 " Resetn $end
$var wire 1 # clock $end
$var wire 1 2 set $end
$var reg 1 3 Q $end
$upscope $end
$upscope $end
$upscope $end
$enddefinitions $end
#0
$dumpvars
x3
02
x1
x0
0/
x.
x-
0,
x+
x*
0)
x(
x'
x&
bx %
1$
0#
0"
bx !
$end
#20
1&
1(
0+
0.
01
1'
0*
0-
00
b10000 !
b10000 %
03
1#
#40
1)
1,
1/
12
0#
0$
1"
#60
1+
b11000 !
b11000 %
1*
1#
#80
0#
#100
1.
b11100 !
b11100 %
1-
1#
#120
0#
#140
11
b11110 !
b11110 %
10
1#
#160
0#
#180
0&
b11111 !
b11111 %
13
1#
#200
0#
#220
0(
b1111 !
b1111 %
0'
1#
#240
0#
#260
0+
b111 !
b111 %
0*
1#
#280
0#
#300
0.
b11 !
b11 %
0-
1#
#320
0#
#340
01
b1 !
b1 %
00
1#
#360
0#
#380
1&
b0 !
b0 %
03
1#
#400
0#
#420
1(
b10000 !
b10000 %
1'
1#
#440
0#
#460
1+
b11000 !
b11000 %
1*
1#
