dsdl/lab11/syncupdownctr.v
module syncupdownctr(x,clock,Resetn,Q);
input x,clock,Resetn;
output [3:0]Q;
tff s0(x|~x,~clock,Resetn,Q[0]);
tff s1((Q[0]&x)|(~x&~Q[0]),~clock,Resetn,Q[1]);
tff s2((Q[1]&Q[0]&x)|(~x&~Q[0]&~Q[1]),~clock,Resetn,Q[2]);
tff s3((Q[2]&Q[1]&Q[0]&x)|(~x&~Q[0]&~Q[1]&~Q[2]),~clock,Resetn,Q[3]);
endmodule

module tff(T,clock,Resetn,Q);
input T,clock,Resetn;
output reg Q;
always @ (posedge clock)
begin
if(!Resetn)
	Q <= 0;
else
	if(T)
		Q <= ~Q;
	else
		Q <= Q;
end
endmodule

dsdl/lab11/syncupdownctr_tb.v
`timescale 1ns/1ns
`include "syncupdownctr.v"
module syncupdownctr_tb();
reg x,clock, Resetn;
wire[3:0] Q;
integer i;
syncupdownctr q5(x,clock,Resetn, Q);

initial
begin
$dumpfile("syncupdownctr_tb.vcd");
$dumpvars(0, syncupdownctr_tb);
clock=0;
forever #10 clock = ~clock;
end

initial
begin
x=0;
Resetn=0; #20;
Resetn=1; #300;
x=1;
Resetn=0; #20;
Resetn=1; #300;
$display("test complete");
$finish;
end
endmodule

dsdl/lab11/syncupdownctr_tb.vcd
$date
	Thu Nov 17 11:25:10 2022
$end
$version
	Icarus Verilog
$end
$timescale
	1ns
$end
$scope module syncupdownctr_tb $end
$var wire 4 ! Q [3:0] $end
$var reg 1 " Resetn $end
$var reg 1 # clock $end
$var reg 1 $ x $end
$scope module q5 $end
$var wire 1 " Resetn $end
$var wire 1 # clock $end
$var wire 1 $ x $end
$var wire 4 % Q [3:0] $end
$scope module s0 $end
$var wire 1 " Resetn $end
$var wire 1 & T $end
$var wire 1 ' clock $end
$var reg 1 ( Q $end
$upscope $end
$scope module s1 $end
$var wire 1 " Resetn $end
$var wire 1 ) T $end
$var wire 1 * clock $end
$var reg 1 + Q $end
$upscope $end
$scope module s2 $end
$var wire 1 " Resetn $end
$var wire 1 , T $end
$var wire 1 - clock $end
$var reg 1 . Q $end
$upscope $end
$scope module s3 $end
$var wire 1 " Resetn $end
$var wire 1 / T $end
$var wire 1 0 clock $end
$var reg 1 1 Q $end
$upscope $end
$upscope $end
$upscope $end
$enddefinitions $end
#0
$dumpvars
01
10
1/
0.
1-
1,
0+
1*
1)
0(
1'
1&
b0 %
0$
0#
0"
b0 !
$end
#10
0'
0*
0-
00
1#
#20
0)
0,
0/
1(
1+
1.
b1111 !
b1111 %
11
1'
1*
1-
10
0#
1"
#30
0'
0*
0-
00
1#
#40
1)
b1110 !
b1110 %
0(
1'
1*
1-
10
0#
#50
0'
0*
0-
00
1#
#60
0)
0,
1(
b1101 !
b1101 %
0+
1'
1*
1-
10
0#
#70
0'
0*
0-
00
1#
#80
1,
1)
b1100 !
b1100 %
0(
1'
1*
1-
10
0#
#90
0'
0*
0-
00
1#
#100
0)
0,
0/
1(
1+
b1011 !
b1011 %
0.
1'
1*
1-
10
0#
#110
0'
0*
0-
00
1#
#120
1)
b1010 !
b1010 %
0(
1'
1*
1-
10
0#
#130
0'
0*
0-
00
1#
#140
0/
0)
0,
1(
b1001 !
b1001 %
0+
1'
1*
1-
10
0#
#150
0'
0*
0-
00
1#
#160
1/
1,
1)
b1000 !
b1000 %
0(
1'
1*
1-
10
0#
#170
0'
0*
0-
00
1#
#180
0)
0,
0/
1(
1+
1.
b111 !
b111 %
01
1'
1*
1-
10
0#
#190
0'
0*
0-
00
1#
#200
1)
b110 !
b110 %
0(
1'
1*
1-
10
0#
#210
0'
0*
0-
00
1#
#220
0)
0,
1(
b101 !
b101 %
0+
1'
1*
1-
10
0#
#230
0'
0*
0-
00
1#
#240
1,
1)
b100 !
b100 %
0(
1'
1*
1-
10
0#
#250
0'
0*
0-
00
1#
#260
0)
0,
0/
1(
1+
b11 !
b11 %
0.
1'
1*
1-
10
0#
#270
0'
0*
0-
00
1#
#280
1)
b10 !
b10 %
0(
1'
1*
1-
10
0#
#290
0'
0*
0-
00
1#
#300
0/
0)
0,
1(
b1 !
b1 %
0+
1'
1*
1-
10
0#
#310
0'
0*
0-
00
1#
#320
b0 !
b0 %
0(
0)
1'
1*
1-
10
0#
0"
1$
#330
0'
0*
0-
00
1#
#340
1)
b1 !
b1 %
1(
1'
1*
1-
10
0#
1"
#350
0'
0*
0-
00
1#
#360
0)
0(
b10 !
b10 %
1+
1'
1*
1-
10
0#
#370
0'
0*
0-
00
1#
#380
1,
1)
b11 !
b11 %
1(
1'
1*
1-
10
0#
#390
0'
0*
0-
00
1#
#400
0,
0)
0(
0+
b100 !
b100 %
1.
1'
1*
1-
10
0#
#410
0'
0*
0-
00
1#
#420
1)
b101 !
b101 %
1(
1'
1*
1-
10
0#
#430
0'
0*
0-
00
1#
#440
0)
0(
b110 !
b110 %
1+
1'
1*
1-
10
0#
#450
0'
0*
0-
00
1#
#460
1/
1,
1)
b111 !
b111 %
1(
1'
1*
1-
10
0#
#470
0'
0*
0-
00
1#
#480
0/
0,
0)
0(
0+
0.
b1000 !
b1000 %
11
1'
1*
1-
10
0#
#490
0'
0*
0-
00
1#
#500
1)
b1001 !
b1001 %
1(
1'
1*
1-
10
0#
#510
0'
0*
0-
00
1#
#520
0)
0(
b1010 !
b1010 %
1+
1'
1*
1-
10
0#
#530
0'
0*
0-
00
1#
#540
1,
1)
b1011 !
b1011 %
1(
1'
1*
1-
10
0#
#550
0'
0*
0-
00
1#
#560
0,
0)
0(
0+
b1100 !
b1100 %
1.
1'
1*
1-
10
0#
#570
0'
0*
0-
00
1#
#580
1)
b1101 !
b1101 %
1(
1'
1*
1-
10
0#
#590
0'
0*
0-
00
1#
#600
0)
0(
b1110 !
b1110 %
1+
1'
1*
1-
10
0#
#610
0'
0*
0-
00
1#
#620
1/
1,
1)
b1111 !
b1111 %
1(
1'
1*
1-
10
0#
#630
0'
0*
0-
00
1#
#640
0/
0,
0)
0(
0+
0.
b0 !
b0 %
01
1'
1*
1-
10
0#
