dsdl/lab9/q1.v
module q1(i,f,En);
input [3:0]i;
input En;
output f;
wire [15:0]c;
dec4to16 s0(i,c,En);
assign f = c[1]|c[3]|c[6]|c[7]|c[9]|c[14]|c[15];

endmodule

module dec4to16(i,f,En);
input [3:0]i;
input En;
output reg [15:0]f;
integer j;
always @ (i,En)
begin
if(En)
begin
for(j=0;j<16;j=j+1)
begin
f[j]=(i==j)?1:0;
end
end
end
endmodule

dsdl/lab9/q1_tb.v
`timescale 1ns/1ns
`include "q1.v"
module q1_tb();
reg [3:0]i;
reg En;
wire f;
integer j;
q1 f1(i,f,En);
initial
begin
$dumpfile("q1_tb.vcd");
$dumpvars(0,q1_tb);
En=1'b1;
for(j=0;j<16;j=j+1)
begin
i=j; #20;
end
$display("test complete");
end
endmodule

dsdl/lab9/q1_tb.vcd
$date
	Thu Nov  3 08:42:23 2022
$end
$version
	Icarus Verilog
$end
$timescale
	1ns
$end
$scope module q1_tb $end
$var wire 1 ! f $end
$var reg 1 " En $end
$var reg 4 # i [3:0] $end
$var integer 32 $ j [31:0] $end
$scope module f1 $end
$var wire 1 " En $end
$var wire 1 ! f $end
$var wire 4 % i [3:0] $end
$var wire 16 & c [15:0] $end
$scope module s0 $end
$var wire 1 " En $end
$var wire 4 ' i [3:0] $end
$var reg 16 ( f [15:0] $end
$var integer 32 ) j [31:0] $end
$upscope $end
$upscope $end
$upscope $end
$enddefinitions $end
#0
$dumpvars
b10000 )
b1 (
b0 '
b1 &
b0 %
b0 $
b0 #
1"
0!
$end
#20
1!
b10 &
b10 (
b10000 )
b1 #
b1 %
b1 '
b1 $
#40
0!
b100 &
b100 (
b10000 )
b10 #
b10 %
b10 '
b10 $
#60
1!
b1000 &
b1000 (
b10000 )
b11 #
b11 %
b11 '
b11 $
#80
0!
b10000 &
b10000 (
b10000 )
b100 #
b100 %
b100 '
b100 $
#100
b100000 &
b100000 (
b10000 )
b101 #
b101 %
b101 '
b101 $
#120
1!
b1000000 &
b1000000 (
b10000 )
b110 #
b110 %
b110 '
b110 $
#140
b10000000 &
b10000000 (
b10000 )
b111 #
b111 %
b111 '
b111 $
#160
0!
b100000000 &
b100000000 (
b10000 )
b1000 #
b1000 %
b1000 '
b1000 $
#180
1!
b1000000000 &
b1000000000 (
b10000 )
b1001 #
b1001 %
b1001 '
b1001 $
#200
0!
b10000000000 &
b10000000000 (
b10000 )
b1010 #
b1010 %
b1010 '
b1010 $
#220
b100000000000 &
b100000000000 (
b10000 )
b1011 #
b1011 %
b1011 '
b1011 $
#240
b1000000000000 &
b1000000000000 (
b10000 )
b1100 #
b1100 %
b1100 '
b1100 $
#260
b10000000000000 &
b10000000000000 (
b10000 )
b1101 #
b1101 %
b1101 '
b1101 $
#280
1!
b100000000000000 &
b100000000000000 (
b10000 )
b1110 #
b1110 %
b1110 '
b1110 $
#300
b1000000000000000 &
b1000000000000000 (
b10000 )
b1111 #
b1111 %
b1111 '
b1111 $
#320
b10000 $
