dsdl/lab9/q3.v
module q3(i,f,En);
input [2:0]i;
input En;
output f;
wire [7:0]c;
twotofour s0(i[1:0],c[3:0],~i[2]&En);
twotofour s1(i[1:0],c[7:4],i[2]&En);
assign f = c[3]|c[5]|c[6]|c[7];
endmodule

module twotofour(i,f,En);
input [1:0]i;
input En;
output reg [3:0]f;
always @ (i,En)
begin

case(En)
0:f=4'd0;
1:
begin
	case(i)
	0:f=4'd1;
	1:f=4'd2;
	2:f=4'd4;
	3:f=4'd8;
	endcase
end
endcase
end
endmodule

dsdl/lab9/q3_tb.v
`timescale 1ns/1ns
`include "q3.v"
module q3_tb();
reg [2:0]i;
reg En;
wire f;
integer j;
q3 f1(i,f,En);
initial
begin
$dumpfile("q3_tb.vcd");
$dumpvars(0,q3_tb);
En=1'b1;
for(j=0;j<8;j=j+1)
begin
i=j; #20;
end
$display("test complete");
end
endmodule

dsdl/lab9/q3_tb.vcd
$date
	Thu Nov  3 08:47:08 2022
$end
$version
	Icarus Verilog
$end
$timescale
	1ns
$end
$scope module q3_tb $end
$var wire 1 ! f $end
$var reg 1 " En $end
$var reg 3 # i [2:0] $end
$var integer 32 $ j [31:0] $end
$scope module f1 $end
$var wire 1 " En $end
$var wire 1 ! f $end
$var wire 3 % i [2:0] $end
$var wire 8 & c [7:0] $end
$scope module s0 $end
$var wire 1 ' En $end
$var wire 2 ( i [1:0] $end
$var reg 4 ) f [3:0] $end
$upscope $end
$scope module s1 $end
$var wire 1 * En $end
$var wire 2 + i [1:0] $end
$var reg 4 , f [3:0] $end
$upscope $end
$upscope $end
$upscope $end
$enddefinitions $end
#0
$dumpvars
b0 ,
b0 +
0*
b1 )
b0 (
1'
b1 &
b0 %
b0 $
b0 #
1"
0!
$end
#20
b10 &
b10 )
b1 (
b1 +
b1 #
b1 %
b1 $
#40
b100 &
b100 )
b10 (
b10 +
b10 #
b10 %
b10 $
#60
1!
b1000 &
b1000 )
b11 (
b11 +
b11 #
b11 %
b11 $
#80
0!
0'
b0 )
b10000 &
b1 ,
1*
b0 (
b0 +
b100 #
b100 %
b100 $
#100
1!
b100000 &
b10 ,
b1 (
b1 +
b101 #
b101 %
b101 $
#120
b1000000 &
b100 ,
b10 (
b10 +
b110 #
b110 %
b110 $
#140
b10000000 &
b1000 ,
b11 (
b11 +
b111 #
b111 %
b111 $
#160
b1000 $
