dsdl/lab3/q2.v
module q2(a,b,c,d,f);
	input a,b,c,d;
	output f;
	
	//left = (((b ~| d) ~| (b ~| c)) ~| ((b ~| d) ~| (b ~| c)))
	//right = (((a ~| c) ~| (a ~| c)) ~| (d ~| d))
	
	//left nor right = ((((b ~| d) ~| (b ~| c)) ~| ((b ~| d) ~| (b ~| c))) ~| (((a ~| c) ~| (a ~| c)) ~| (d ~| d)))
	
	assign f = (((((b ~| d) ~| (b ~| c)) ~| ((b ~| d) ~| (b ~| c))) ~| (((a ~| c) ~| (a ~| c)) ~| (d ~| d))) ~| ((((b ~| d) ~| (b ~| c)) ~| ((b ~| d) ~| (b ~| c))) ~| (((a ~| c) ~| (a ~| c)) ~| (d ~| d)))) ;
	
	/*
	nor (h,b,d);
	nor (i,b,c);
	nor (j,a,c);
	nor (jCompli,j,j);
	nor (k,h,i);
	nor (kCompli,k,k);
	nor (dCompli,d,d);
	nor (l,jCompli,dCompli);
	nor (m,kCompli,l);
	nor (f,m,m); */
	
	//Correct answer:
	//assign f = ((~b & ~d) | (~b & ~c) | (~a & ~c & ~d));

endmodule

dsdl/lab3/q2_tb.v
`timescale 1ns/1ns
`include "q2.v" 

module q2_tb();
reg a,b,c,d;
wire f;

q2 ex1(a,b,c,d,f);
initial 
begin

	$dumpfile("q2_tb.vcd");
	$dumpvars(0,q2_tb);
	
	a=1'b0; b=1'b0; c=1'b0; d=1'b0;
	#20;
	
	a=1'b0; b=1'b0; c=1'b0; d=1'b1;
	#20;
	
	a=1'b0; b=1'b0; c=1'b1; d=1'b0;
	#20;
	
	a=1'b0; b=1'b0; c=1'b1; d=1'b1;
	#20;
	
	a=1'b0; b=1'b1; c=1'b0; d=1'b0;
	#20;
	
	a=1'b0; b=1'b1; c=1'b0; d=1'b1;
	#20;
	
	a=1'b0; b=1'b1; c=1'b1; d=1'b0;
	#20;
	
	a=1'b0; b=1'b1; c=1'b1; d=1'b1;
	#20;
	
	a=1'b1; b=1'b0; c=1'b0; d=1'b0;
	#20;
	
	a=1'b1; b=1'b0; c=1'b0; d=1'b1;
	#20;
	
	a=1'b1; b=1'b0; c=1'b1; d=1'b0;
	#20;
	
	a=1'b1; b=1'b0; c=1'b1; d=1'b1;
	#20;
	
	a=1'b1; b=1'b1; c=1'b0; d=1'b0;
	#20;
	
	a=1'b1; b=1'b1; c=1'b0; d=1'b1;
	#20;
	
	a=1'b1; b=1'b1; c=1'b1; d=1'b0;
	#20;
	
	a=1'b1; b=1'b1; c=1'b1; d=1'b1;
	#20;
	$display("Test Complete");
end

endmodule

dsdl/lab3/q2_tb.vcd
$date
	Thu Sep  8 09:20:12 2022
$end
$version
	Icarus Verilog
$end
$timescale
	1ns
$end
$scope module q2_tb $end
$var wire 1 ! f $end
$var reg 1 " a $end
$var reg 1 # b $end
$var reg 1 $ c $end
$var reg 1 % d $end
$scope module ex1 $end
$var wire 1 " a $end
$var wire 1 # b $end
$var wire 1 $ c $end
$var wire 1 % d $end
$var wire 1 ! f $end
$upscope $end
$upscope $end
$enddefinitions $end
#0
$dumpvars
0%
0$
0#
0"
1!
$end
#20
1%
#40
0%
1$
#60
0!
1%
#80
0%
0$
1#
#100
1!
1%
#120
0!
0%
1$
#140
1%
#160
1!
0%
0$
0#
1"
#180
1%
#200
0%
1$
#220
0!
1%
#240
0%
0$
1#
#260
1%
#280
0%
1$
#300
1%
