dsdl/lab3/q3.v

module q3(a,b,c,d,e,f);
	input a,b,c,d,e;
	output f;
	
	
	or (h,~a,b);
	and (g,e,h);
	not (gCompli,g);
	and (t1,~c,~d,g);
	and (t2,c,d,g);
	and (t3,~c,d,gCompli);
	or (f,t1,t2,t3); 
	
	//assign f = ((~c & ~d & (e & (~a | b))) | (c & d & (e & (~a | b))) | (~c & d & (~e | (a & ~b))));
	
endmodule

dsdl/lab3/q3_tb.v
`timescale 1ns/1ns
`include "q3.v" 

module q3_tb();
reg a,b,c,d,e;
wire f;

q3 ex1(a,b,c,d,e,f);
initial 
begin

	$dumpfile("q3_tb.vcd");
	$dumpvars(0,q3_tb);
	
	a=0; b=0; c=0; d=0; e=0;
	#20;
	
	a=0; b=0; c=0; d=0; e=1;
	#20;
	
	a=0; b=0; c=0; d=1; e=0;
	#20;
	
	a=0; b=0; c=0; d=1; e=1;
	#20;
	
	a=0; b=0; c=1; d=0; e=0;
	#20;
	
	a=0; b=0; c=1; d=0; e=1;
	#20;
	
	a=0; b=0; c=1; d=1; e=0;
	#20;
	
	a=0; b=0; c=1; d=1; e=1;
	#20;
	
	a=0; b=1; c=0; d=0; e=0;
	#20;
	
	a=0; b=1; c=0; d=0; e=1;
	#20;
	
	a=0; b=1; c=0; d=1; e=0;
	#20;
	
	a=0; b=1; c=0; d=1; e=1;
	#20;
	
	a=0; b=1; c=1; d=0; e=0;
	#20;
	
	a=0; b=1; c=1; d=0; e=1;
	#20;
	
	a=0; b=1; c=1; d=1; e=0;
	#20;
	
	a=0; b=1; c=1; d=1; e=1;
	#20;
	
	a=1; b=0; c=0; d=0; e=0;
	#20;
	
	a=1; b=0; c=0; d=0; e=1;
	#20;
	
	a=1; b=0; c=0; d=1; e=0;
	#20;
	
	a=1; b=0; c=0; d=1; e=1;
	#20;
	
	a=1; b=0; c=1; d=0; e=0;
	#20;
	
	a=1; b=0; c=1; d=0; e=1;
	#20;
	
	a=1; b=0; c=1; d=1; e=0;
	#20;
	
	a=1; b=0; c=1; d=1; e=1;
	#20;
	
	a=1; b=1; c=0; d=0; e=0;
	#20;
	
	a=1; b=1; c=0; d=0; e=1;
	#20;
	
	a=1; b=1; c=0; d=1; e=0;
	#20;
	
	a=1; b=1; c=0; d=1; e=1;
	#20;
	
	a=1; b=1; c=1; d=0; e=0;
	#20;
	
	a=1; b=1; c=1; d=0; e=1;
	#20;
	
	a=1; b=1; c=1; d=1; e=0;
	#20;
	
	a=1; b=1; c=1; d=1; e=1;
	#20;
	
	$display("Test Complete");
end

endmodule

dsdl/lab3/q3_tb.vcd
$date
	Thu Sep  8 09:36:58 2022
$end
$version
	Icarus Verilog
$end
$timescale
	1ns
$end
$scope module q3_tb $end
$var wire 1 ! f $end
$var reg 1 " a $end
$var reg 1 # b $end
$var reg 1 $ c $end
$var reg 1 % d $end
$var reg 1 & e $end
$scope module ex1 $end
$var wire 1 " a $end
$var wire 1 # b $end
$var wire 1 $ c $end
$var wire 1 % d $end
$var wire 1 & e $end
$var wire 1 ! f $end
$var wire 1 ' g $end
$var wire 1 ( gCompli $end
$var wire 1 ) h $end
$var wire 1 * t1 $end
$var wire 1 + t2 $end
$var wire 1 , t3 $end
$upscope $end
$upscope $end
$enddefinitions $end
#0
$dumpvars
0,
0+
0*
1)
1(
0'
0&
0%
0$
0#
0"
0!
$end
#20
1!
0(
1*
1'
1&
#40
1,
1!
1(
0*
0'
0&
1%
#60
0!
0,
0(
1'
1&
#80
1(
0'
0&
0%
1$
#100
0(
1'
1&
#120
1(
0!
0'
0+
0&
1%
#140
1!
0(
1+
1'
1&
#160
1(
0!
0'
0+
0&
0%
0$
1#
#180
1!
0(
1*
1'
1&
#200
1,
1!
1(
0*
0'
0&
1%
#220
0!
0,
0(
1'
1&
#240
1(
0'
0&
0%
1$
#260
0(
1'
1&
#280
1(
0!
0'
0+
0&
1%
#300
1!
0(
1+
1'
1&
#320
1(
0!
0'
0+
0)
0&
0%
0$
0#
1"
#340
1&
#360
1!
1,
0&
1%
#380
1&
#400
0!
0,
0&
0%
1$
#420
1&
#440
0&
1%
#460
1&
#480
1)
0&
0%
0$
1#
#500
1!
0(
1*
1'
1&
#520
1,
1!
1(
0*
0'
0&
1%
#540
0!
0,
0(
1'
1&
#560
1(
0'
0&
0%
1$
#580
0(
1'
1&
#600
1(
0!
0'
0+
0&
1%
#620
1!
0(
1+
1'
1&
